nginx_parser-0.1.dist-info/DESCRIPTION.rst
nginx_parser-0.1.dist-info/entry_points.txt
nginx_parser-0.1.dist-info/METADATA
nginx_parser-0.1.dist-info/metadata.json
nginx_parser-0.1.dist-info/RECORD
nginx_parser-0.1.dist-info/top_level.txt
nginx_parser-0.1.dist-info/WHEEL
src/__init__.py
src/conf.py
src/parser.py
src/picasso.py
src/store.py
