Metadata-Version: 2.0
Name: nginx-parser
Version: 0.1
Summary: A simple parser for nginx logs
Home-page: https://github.com/davarisg/nginx-parser
Author: George Davaris
Author-email: davarisg@gmail.com
License: MIT
Platform: UNKNOWN
Classifier: License :: OSI Approved :: MIT License
Classifier: Development Status :: 4 - Beta
Classifier: Programming Language :: Python :: 2.7
Classifier: Programming Language :: Python :: 3.5
Requires-Dist: blessed (>=1.14.2)
Requires-Dist: PyYAML (>=3.12)
